easy_open_ai/__init__.py
easy_open_ai/docstrings.py
easy_open_ai/functions/__init__.py
easy_open_ai/functions/picture.py
easy_open_ai/functions/stream_text.py
easy_open_ai/functions/text.py
easy_open_ai/models/__init__.py
easy_open_ai/models/api_key.py
easy_open_ai/models/error_handling.py
easy_open_ai/models/picture.py
easy_open_ai/models/stream_text.py
easy_open_ai/models/text.py
easy_open_ai-0.2.0.dist-info/entry_points.txt
easy_open_ai-0.2.0.dist-info/METADATA
easy_open_ai-0.2.0.dist-info/WHEEL
easy_open_ai-0.2.0.dist-info/RECORD
