Metadata-Version: 2.1
Name: easy-open-ai
Version: 0.2.0
Summary: This is my first REAL package.
Author: ani
Author-email: 125677472+anilev6@users.noreply.github.com
Requires-Python: >=3.11,<4.0
Classifier: Programming Language :: Python :: 3
Classifier: Programming Language :: Python :: 3.11
Requires-Dist: astor (>=0.8.1,<0.9.0)
Requires-Dist: icecream (>=2.1.3,<3.0.0)
Requires-Dist: openai (>=0.28.1,<0.29.0)
Requires-Dist: pytest (>=7.4.3,<8.0.0)
Requires-Dist: tiktoken (>=0.5.1,<0.6.0)
